kash/__init__.py
kash/secret_client.py
kash-0.1.0.dist-info/DESCRIPTION.rst
kash-0.1.0.dist-info/METADATA
kash-0.1.0.dist-info/metadata.json
kash-0.1.0.dist-info/RECORD
kash-0.1.0.dist-info/top_level.txt
kash-0.1.0.dist-info/WHEEL
