Metadata-Version: 2.0
Name: kash
Version: 0.1.0
Summary: Kash API Python Client
Home-page: http://code.google.com/p/gyp
Author: Kash
Author-email: developers@withkash.com
License: UNKNOWN
Platform: UNKNOWN
Requires-Dist: requests
